LICENSE
README.md
setup.cfg
setup.py
AwareDB/__init__.py
AwareDB/api.py
AwareDB.egg-info/PKG-INFO
AwareDB.egg-info/SOURCES.txt
AwareDB.egg-info/dependency_links.txt
AwareDB.egg-info/requires.txt
AwareDB.egg-info/top_level.txt
awaredb/__init__.py
awaredb/api.py
awaredb.egg-info/PKG-INFO
awaredb.egg-info/SOURCES.txt
awaredb.egg-info/dependency_links.txt
awaredb.egg-info/requires.txt
awaredb.egg-info/top_level.txt